scikeo/__init__.py
scikeo/atmosCorr.py
scikeo/calkmeans.py
scikeo/calmla.py
scikeo/deeplearning.py
scikeo/fusionrs.py
scikeo/linearTrend.py
scikeo/mla.py
scikeo/pca.py
scikeo/plot.py
scikeo/process.py
scikeo/rkmeans.py
scikeo/sma.py
scikeo/tassCap.py
scikeo/writeRaster.py
scikeo-0.2.44.dist-info/licenses/LICENSE
scikeo-0.2.44.dist-info/METADATA
scikeo-0.2.44.dist-info/WHEEL
scikeo-0.2.44.dist-info/dependency_links.txt
scikeo-0.2.44.dist-info/top_level.txt
scikeo-0.2.44.dist-info/RECORD
