Metadata-Version: 2.4
Name: scikeo
Version: 0.2.44
Summary: Remote Sensing Tools
Home-page: https://github.com/yotarazona/scikit-eo
Author: Yonatan Tarazona
Author-email: ytarazona09@gmail.com
License: Apache Software License 2.0
Keywords: scikeo
Classifier: Intended Audience :: Developers
Classifier: License :: OSI Approved :: Apache Software License
Classifier: Natural Language :: English
Classifier: Programming Language :: Python :: 3.8
Classifier: Programming Language :: Python :: 3.9
Classifier: Programming Language :: Python :: 3.10
Classifier: Programming Language :: Python :: 3.11
Requires-Python: >=3.8
License-File: LICENSE
Requires-Dist: pandas
Requires-Dist: matplotlib
Requires-Dist: rasterio
Requires-Dist: seaborn
Requires-Dist: statsmodels
Requires-Dist: scikit-learn
Requires-Dist: scipy
Requires-Dist: pytest
Requires-Dist: dbfread
Requires-Dist: fiona
Requires-Dist: geopandas
Requires-Dist: tensorflow
Requires-Dist: numpy
Dynamic: author
Dynamic: author-email
Dynamic: classifier
Dynamic: description
Dynamic: description-content-type
Dynamic: home-page
Dynamic: keywords
Dynamic: license
Dynamic: license-file
Dynamic: requires-dist
Dynamic: requires-python
Dynamic: summary
